README.md
setup.py
friendly_states/__init__.py
friendly_states/core.py
friendly_states/django.py
friendly_states/exceptions.py
friendly_states/utils.py
friendly_states.egg-info/PKG-INFO
friendly_states.egg-info/SOURCES.txt
friendly_states.egg-info/dependency_links.txt
friendly_states.egg-info/requires.txt
friendly_states.egg-info/top_level.txt