Metadata-Version: 2.1
Name: friendly-states
Version: 0.1.0
Summary: Declarative, explicit, tool-friendly finite state machines in Python
Home-page: http://github.com/alexmojaki/friendly_states
Author: Alex Hall
Author-email: alex.mojaki@gmail.com
License: MIT
Platform: UNKNOWN
Classifier: Intended Audience :: Developers
Classifier: Programming Language :: Python :: 3.7
Classifier: License :: OSI Approved :: MIT License
Classifier: Operating System :: OS Independent
Provides-Extra: tests
